fastmcp_apps_sdk/__init__.py
fastmcp_apps_sdk/widgets.py
fastmcp_apps_sdk-1.0.0.dist-info/METADATA
fastmcp_apps_sdk-1.0.0.dist-info/WHEEL
fastmcp_apps_sdk-1.0.0.dist-info/RECORD
