Metadata-Version: 2.4
Name: fastmcp-apps-sdk
Version: 1.0.0
Summary: Widgets SDK for FastMCP targeting OpenAI Apps SDK (outputTemplate + widget helpers).
Requires-Python: >=3.12
Requires-Dist: fastmcp>=2.12.4
